bayes/__init__.py
bayes/client/__init__.py
bayes/client/base.py
bayes/client/dataset_client.py
bayes/client/dataset_list_client.py
bayes/client/dataset_upload_client.py
bayes/client/dataset_version_client.py
bayes/client/gear_client.py
bayes/client/job_run_client.py
bayes/client/minio_storage_client.py
bayes/client/org_client.py
bayes/client/resource_client.py
bayes/client/runtime_client.py
bayes/client/ssh_client.py
bayes/client/status_client.py
bayes/client/user_client.py
bayes/commands/__init__.py
bayes/commands/data.py
bayes/commands/gear.py
bayes/commands/hpc.py
bayes/commands/org.py
bayes/commands/ssh.py
bayes/error.py
bayes/model/__init__.py
bayes/model/dataset.py
bayes/model/dataset_version.py
bayes/model/file/__init__.py
bayes/model/file/bayes_file.py
bayes/model/file/data_bindings.py
bayes/model/file/openbayes_gear.py
bayes/model/file/openbayes_ignore.py
bayes/model/file/openbayes_yaml.py
bayes/model/file/settings.py
bayes/model/party.py
bayes/model/resource.py
bayes/model/runtime.py
bayes/root.py
bayes/templates/__init__.py
bayes/templates/openbayes_zh-Hans.yaml
bayes/templates/openbayesignore.yaml
bayes/usercases/__init__.py
bayes/usercases/archive_usecase.py
bayes/usercases/auth_usecase.py
bayes/usercases/dataset_list_usecase.py
bayes/usercases/dataset_usecase.py
bayes/usercases/dataset_version_usecase.py
bayes/usercases/disk_usecase.py
bayes/usercases/gear_download_usecese.py
bayes/usercases/gear_logs_usecase.py
bayes/usercases/gear_run_usecase.py
bayes/usercases/gear_usecase.py
bayes/usercases/minio_storage_usecase.py
bayes/usercases/open_usecase.py
bayes/usercases/org_usecase.py
bayes/usercases/resource_usecase.py
bayes/usercases/runtime_usecase.py
bayes/usercases/ssh_usecase.py
bayes/usercases/switch_usercase.py
bayes/usercases/upload_state_manager.py
bayes/utils/__init__.py
bayes/utils/add_global_param.py
bayes/utils.py
openbayestool/__init__.py
openbayestool/config.py
openbayestool/http_client.py
openbayestool/jwt_client.py
openbayes_cli-0.23.0.dist-info/METADATA
openbayes_cli-0.23.0.dist-info/WHEEL
openbayes_cli-0.23.0.dist-info/entry_points.txt
openbayes_cli-0.23.0.dist-info/RECORD
